<?xml version="1.0"?>
<Vulnerability xmlns:xsi="http://www.w3.org/2001/XMLSchema-instance" xmlns:xsd="http://www.w3.org/2001/XMLSchema" Lang="INTL" Vul_ID="RHBA-2014-0989" Revision="1" CVE_ID="">
  <Status>Enabled</Status>
  <Patches>
    <Patch UniqueFilename="*libgudev1-208-11.el7_0.2.i686.rpm" Silent="CRSNo" Reboot="RNo" Download="DManual">
      <Name>libgudev1-208-11.el7_0.2.i686.rpm</Name>
      <Comments />
      <URL />
      <State>Enabled</State>
      <Files>
        <File>
          <Path>libgudev1::i686</Path>
          <FileDate>0001-01-01T00:00:00.0000000</FileDate>
          <FileSize>0</FileSize>
          <Checksum>bf4dfdbaa1233a1ab207efefa112e80bc38bf31e03e9370e6da74ba042e747e0</Checksum>
          <Version>208-11.el7_0.2</Version>
          <CommandID>e</CommandID>
          <Flags>P</Flags>
        </File>
      </Files>
      <Products>
        <ID>55405</ID>
      </Products>
      <Platforms>
        <ID>rhel7_x86_64</ID>
      </Platforms>
      <CustVars />
      <Cmds>
        <Cmd Type="shellscript">
          <Args>
            <Arg N="scriptcode" V="#!/bin/bash&#xA;&#xA;function updatepk()&#xA;{&#xA; if [ ! -z $1 ]; then&#xA;   if [ -e /var/run/yum.pid ];then &#xA;    exit 10  &#xA;   fi&#xA;   result=`yum -y update $1 2&gt;&amp;1` &#xA;   status=$? &#xA;   commandexist=`echo $result | grep -E &quot;yum: command not found&quot;`&#xA;   if [ &quot;$commandexist&quot; != &quot;&quot; ]; then&#xA;     exit 8&#xA;   fi&#xA;   &#xA;    commandexist=`echo $result | grep -E &quot;yum: No such file or directory&quot;`&#xA;   if [ &quot;$commandexist&quot; != &quot;&quot; ]; then&#xA;     exit 8&#xA;   fi&#xA;   &#xA;   islock=`echo $result | grep -E &quot;lock /var/run/yum.pid&quot;`&#xA;   &#xA;   if [ &quot;$islock&quot; != &quot;&quot; ]; then&#xA;     exit 10&#xA;   fi&#xA;   &#xA;   islock=`echo $result | grep -E &quot;/var/run/yum.pid: another copy is running&quot;`&#xA;   &#xA;   if [ &quot;$islock&quot; != &quot;&quot; ]; then&#xA;     exit 10&#xA;   fi&#xA;   &#xA;   isnotconnected=`echo $result | grep -E &quot;There was an error communicating with RHN&quot;`&#xA;   if [ &quot;$isnotconnected&quot; != &quot;&quot; ]; then&#xA;     exit 9&#xA;   fi&#xA;   &#xA;   isnotconnected=`echo $result | grep -E &quot;This system is not registered with RHN&quot;`&#xA;   if [ &quot;$isnotconnected&quot; != &quot;&quot; ]; then&#xA;     exit 9&#xA;   fi&#xA;   &#xA;    isnotconnected=`echo $result | grep -E &quot;No Repositories Available to Set Up&quot;`&#xA;   if [ &quot;$isnotconnected&quot; != &quot;&quot; ]; then&#xA;     exit 9&#xA;   fi&#xA;    isnotconnected=`echo $result | grep -E &quot;Error Class Code: 9 Error Class Info: Invalid System Credentials&quot;`&#xA;   if [ &quot;$isnotconnected&quot; != &quot;&quot; ]; then&#xA;     exit 9&#xA;   fi&#xA;    isscriptletfailed=`echo $result | grep -E &quot;error:&quot; | grep -E &quot;scriptlet failed, exit status 255&quot;`&#xA;    if [ &quot;$isscriptletfailed&quot; != &quot;&quot; ]; then&#xA;     exit 6&#xA;   fi&#xA;   if [ $status -ne 0 ];then&#xA;     exit 7&#xA;   fi &#xA; fi&#xA;}&#xA;updatepk libgudev1  &#xA;&#xA;exit 0" />
          </Args>
        </Cmd>
      </Cmds>
    </Patch>
    <Patch UniqueFilename="*libgudev1-208-11.el7_0.2.x86_64.rpm" Silent="CRSNo" Reboot="RNo" Download="DManual">
      <Name>libgudev1-208-11.el7_0.2.x86_64.rpm</Name>
      <Comments />
      <URL />
      <State>Enabled</State>
      <Files>
        <File>
          <Path>libgudev1::x86_64</Path>
          <FileDate>0001-01-01T00:00:00.0000000</FileDate>
          <FileSize>0</FileSize>
          <Checksum>f126ff8b4249065c620f22eaf316df4aa03b1893214a820ee9ac704ff9cfc743</Checksum>
          <Version>208-11.el7_0.2</Version>
          <CommandID>e</CommandID>
          <Flags>P</Flags>
        </File>
      </Files>
      <Products>
        <ID>55406</ID>
      </Products>
      <Platforms>
        <ID>rhel7_x86_64</ID>
      </Platforms>
      <CustVars />
      <Cmds>
        <Cmd Type="shellscript">
          <Args>
            <Arg N="scriptcode" V="#!/bin/bash&#xA;&#xA;function updatepk()&#xA;{&#xA; if [ ! -z $1 ]; then&#xA;   if [ -e /var/run/yum.pid ];then &#xA;    exit 10  &#xA;   fi&#xA;   result=`yum -y update $1 2&gt;&amp;1` &#xA;   status=$? &#xA;   commandexist=`echo $result | grep -E &quot;yum: command not found&quot;`&#xA;   if [ &quot;$commandexist&quot; != &quot;&quot; ]; then&#xA;     exit 8&#xA;   fi&#xA;   &#xA;    commandexist=`echo $result | grep -E &quot;yum: No such file or directory&quot;`&#xA;   if [ &quot;$commandexist&quot; != &quot;&quot; ]; then&#xA;     exit 8&#xA;   fi&#xA;   &#xA;   islock=`echo $result | grep -E &quot;lock /var/run/yum.pid&quot;`&#xA;   &#xA;   if [ &quot;$islock&quot; != &quot;&quot; ]; then&#xA;     exit 10&#xA;   fi&#xA;   &#xA;   islock=`echo $result | grep -E &quot;/var/run/yum.pid: another copy is running&quot;`&#xA;   &#xA;   if [ &quot;$islock&quot; != &quot;&quot; ]; then&#xA;     exit 10&#xA;   fi&#xA;   &#xA;   isnotconnected=`echo $result | grep -E &quot;There was an error communicating with RHN&quot;`&#xA;   if [ &quot;$isnotconnected&quot; != &quot;&quot; ]; then&#xA;     exit 9&#xA;   fi&#xA;   &#xA;   isnotconnected=`echo $result | grep -E &quot;This system is not registered with RHN&quot;`&#xA;   if [ &quot;$isnotconnected&quot; != &quot;&quot; ]; then&#xA;     exit 9&#xA;   fi&#xA;   &#xA;    isnotconnected=`echo $result | grep -E &quot;No Repositories Available to Set Up&quot;`&#xA;   if [ &quot;$isnotconnected&quot; != &quot;&quot; ]; then&#xA;     exit 9&#xA;   fi&#xA;    isnotconnected=`echo $result | grep -E &quot;Error Class Code: 9 Error Class Info: Invalid System Credentials&quot;`&#xA;   if [ &quot;$isnotconnected&quot; != &quot;&quot; ]; then&#xA;     exit 9&#xA;   fi&#xA;    isscriptletfailed=`echo $result | grep -E &quot;error:&quot; | grep -E &quot;scriptlet failed, exit status 255&quot;`&#xA;    if [ &quot;$isscriptletfailed&quot; != &quot;&quot; ]; then&#xA;     exit 6&#xA;   fi&#xA;   if [ $status -ne 0 ];then&#xA;     exit 7&#xA;   fi &#xA; fi&#xA;}&#xA;updatepk libgudev1  &#xA;&#xA;exit 0" />
          </Args>
        </Cmd>
      </Cmds>
    </Patch>
    <Patch UniqueFilename="*libgudev1-devel-208-11.el7_0.2.i686.rpm" Silent="CRSNo" Reboot="RNo" Download="DManual">
      <Name>libgudev1-devel-208-11.el7_0.2.i686.rpm</Name>
      <Comments />
      <URL />
      <State>Enabled</State>
      <Files>
        <File>
          <Path>libgudev1-devel::i686</Path>
          <FileDate>0001-01-01T00:00:00.0000000</FileDate>
          <FileSize>0</FileSize>
          <Checksum>a5ed0e36e4ab1fc61a932237c3b50b42e9b232c70c910e73f0bd77b2f9731f06</Checksum>
          <Version>208-11.el7_0.2</Version>
          <CommandID>e</CommandID>
          <Flags>P</Flags>
        </File>
      </Files>
      <Products>
        <ID>55407</ID>
      </Products>
      <Platforms>
        <ID>rhel7_x86_64</ID>
      </Platforms>
      <CustVars />
      <Cmds>
        <Cmd Type="shellscript">
          <Args>
            <Arg N="scriptcode" V="#!/bin/bash&#xA;&#xA;function updatepk()&#xA;{&#xA; if [ ! -z $1 ]; then&#xA;   if [ -e /var/run/yum.pid ];then &#xA;    exit 10  &#xA;   fi&#xA;   result=`yum -y update $1 2&gt;&amp;1` &#xA;   status=$? &#xA;   commandexist=`echo $result | grep -E &quot;yum: command not found&quot;`&#xA;   if [ &quot;$commandexist&quot; != &quot;&quot; ]; then&#xA;     exit 8&#xA;   fi&#xA;   &#xA;    commandexist=`echo $result | grep -E &quot;yum: No such file or directory&quot;`&#xA;   if [ &quot;$commandexist&quot; != &quot;&quot; ]; then&#xA;     exit 8&#xA;   fi&#xA;   &#xA;   islock=`echo $result | grep -E &quot;lock /var/run/yum.pid&quot;`&#xA;   &#xA;   if [ &quot;$islock&quot; != &quot;&quot; ]; then&#xA;     exit 10&#xA;   fi&#xA;   &#xA;   islock=`echo $result | grep -E &quot;/var/run/yum.pid: another copy is running&quot;`&#xA;   &#xA;   if [ &quot;$islock&quot; != &quot;&quot; ]; then&#xA;     exit 10&#xA;   fi&#xA;   &#xA;   isnotconnected=`echo $result | grep -E &quot;There was an error communicating with RHN&quot;`&#xA;   if [ &quot;$isnotconnected&quot; != &quot;&quot; ]; then&#xA;     exit 9&#xA;   fi&#xA;   &#xA;   isnotconnected=`echo $result | grep -E &quot;This system is not registered with RHN&quot;`&#xA;   if [ &quot;$isnotconnected&quot; != &quot;&quot; ]; then&#xA;     exit 9&#xA;   fi&#xA;   &#xA;    isnotconnected=`echo $result | grep -E &quot;No Repositories Available to Set Up&quot;`&#xA;   if [ &quot;$isnotconnected&quot; != &quot;&quot; ]; then&#xA;     exit 9&#xA;   fi&#xA;    isnotconnected=`echo $result | grep -E &quot;Error Class Code: 9 Error Class Info: Invalid System Credentials&quot;`&#xA;   if [ &quot;$isnotconnected&quot; != &quot;&quot; ]; then&#xA;     exit 9&#xA;   fi&#xA;    isscriptletfailed=`echo $result | grep -E &quot;error:&quot; | grep -E &quot;scriptlet failed, exit status 255&quot;`&#xA;    if [ &quot;$isscriptletfailed&quot; != &quot;&quot; ]; then&#xA;     exit 6&#xA;   fi&#xA;   if [ $status -ne 0 ];then&#xA;     exit 7&#xA;   fi &#xA; fi&#xA;}&#xA;updatepk libgudev1-devel  &#xA;&#xA;exit 0" />
          </Args>
        </Cmd>
      </Cmds>
    </Patch>
    <Patch UniqueFilename="*libgudev1-devel-208-11.el7_0.2.x86_64.rpm" Silent="CRSNo" Reboot="RNo" Download="DManual">
      <Name>libgudev1-devel-208-11.el7_0.2.x86_64.rpm</Name>
      <Comments />
      <URL />
      <State>Enabled</State>
      <Files>
        <File>
          <Path>libgudev1-devel::x86_64</Path>
          <FileDate>0001-01-01T00:00:00.0000000</FileDate>
          <FileSize>0</FileSize>
          <Checksum>1a05bdd92cb4da4b96862f0cccc0c89a3b96cc3ce378cddbef9eecc247c20022</Checksum>
          <Version>208-11.el7_0.2</Version>
          <CommandID>e</CommandID>
          <Flags>P</Flags>
        </File>
      </Files>
      <Products>
        <ID>55408</ID>
      </Products>
      <Platforms>
        <ID>rhel7_x86_64</ID>
      </Platforms>
      <CustVars />
      <Cmds>
        <Cmd Type="shellscript">
          <Args>
            <Arg N="scriptcode" V="#!/bin/bash&#xA;&#xA;function updatepk()&#xA;{&#xA; if [ ! -z $1 ]; then&#xA;   if [ -e /var/run/yum.pid ];then &#xA;    exit 10  &#xA;   fi&#xA;   result=`yum -y update $1 2&gt;&amp;1` &#xA;   status=$? &#xA;   commandexist=`echo $result | grep -E &quot;yum: command not found&quot;`&#xA;   if [ &quot;$commandexist&quot; != &quot;&quot; ]; then&#xA;     exit 8&#xA;   fi&#xA;   &#xA;    commandexist=`echo $result | grep -E &quot;yum: No such file or directory&quot;`&#xA;   if [ &quot;$commandexist&quot; != &quot;&quot; ]; then&#xA;     exit 8&#xA;   fi&#xA;   &#xA;   islock=`echo $result | grep -E &quot;lock /var/run/yum.pid&quot;`&#xA;   &#xA;   if [ &quot;$islock&quot; != &quot;&quot; ]; then&#xA;     exit 10&#xA;   fi&#xA;   &#xA;   islock=`echo $result | grep -E &quot;/var/run/yum.pid: another copy is running&quot;`&#xA;   &#xA;   if [ &quot;$islock&quot; != &quot;&quot; ]; then&#xA;     exit 10&#xA;   fi&#xA;   &#xA;   isnotconnected=`echo $result | grep -E &quot;There was an error communicating with RHN&quot;`&#xA;   if [ &quot;$isnotconnected&quot; != &quot;&quot; ]; then&#xA;     exit 9&#xA;   fi&#xA;   &#xA;   isnotconnected=`echo $result | grep -E &quot;This system is not registered with RHN&quot;`&#xA;   if [ &quot;$isnotconnected&quot; != &quot;&quot; ]; then&#xA;     exit 9&#xA;   fi&#xA;   &#xA;    isnotconnected=`echo $result | grep -E &quot;No Repositories Available to Set Up&quot;`&#xA;   if [ &quot;$isnotconnected&quot; != &quot;&quot; ]; then&#xA;     exit 9&#xA;   fi&#xA;    isnotconnected=`echo $result | grep -E &quot;Error Class Code: 9 Error Class Info: Invalid System Credentials&quot;`&#xA;   if [ &quot;$isnotconnected&quot; != &quot;&quot; ]; then&#xA;     exit 9&#xA;   fi&#xA;    isscriptletfailed=`echo $result | grep -E &quot;error:&quot; | grep -E &quot;scriptlet failed, exit status 255&quot;`&#xA;    if [ &quot;$isscriptletfailed&quot; != &quot;&quot; ]; then&#xA;     exit 6&#xA;   fi&#xA;   if [ $status -ne 0 ];then&#xA;     exit 7&#xA;   fi &#xA; fi&#xA;}&#xA;updatepk libgudev1-devel  &#xA;&#xA;exit 0" />
          </Args>
        </Cmd>
      </Cmds>
    </Patch>
    <Patch UniqueFilename="*systemd-208-11.el7_0.2.x86_64.rpm" Silent="CRSNo" Reboot="RNo" Download="DManual">
      <Name>systemd-208-11.el7_0.2.x86_64.rpm</Name>
      <Comments />
      <URL />
      <State>Enabled</State>
      <Files>
        <File>
          <Path>systemd::x86_64</Path>
          <FileDate>0001-01-01T00:00:00.0000000</FileDate>
          <FileSize>0</FileSize>
          <Checksum>da4c8450a644d5da188eeda6ad725e65e707a87d6152c00d09997994d070290b</Checksum>
          <Version>208-11.el7_0.2</Version>
          <CommandID>e</CommandID>
          <Flags>P</Flags>
        </File>
      </Files>
      <Products>
        <ID>55409</ID>
      </Products>
      <Platforms>
        <ID>rhel7_x86_64</ID>
      </Platforms>
      <CustVars />
      <Cmds>
        <Cmd Type="shellscript">
          <Args>
            <Arg N="scriptcode" V="#!/bin/bash&#xA;&#xA;function updatepk()&#xA;{&#xA; if [ ! -z $1 ]; then&#xA;   if [ -e /var/run/yum.pid ];then &#xA;    exit 10  &#xA;   fi&#xA;   result=`yum -y update $1 2&gt;&amp;1` &#xA;   status=$? &#xA;   commandexist=`echo $result | grep -E &quot;yum: command not found&quot;`&#xA;   if [ &quot;$commandexist&quot; != &quot;&quot; ]; then&#xA;     exit 8&#xA;   fi&#xA;   &#xA;    commandexist=`echo $result | grep -E &quot;yum: No such file or directory&quot;`&#xA;   if [ &quot;$commandexist&quot; != &quot;&quot; ]; then&#xA;     exit 8&#xA;   fi&#xA;   &#xA;   islock=`echo $result | grep -E &quot;lock /var/run/yum.pid&quot;`&#xA;   &#xA;   if [ &quot;$islock&quot; != &quot;&quot; ]; then&#xA;     exit 10&#xA;   fi&#xA;   &#xA;   islock=`echo $result | grep -E &quot;/var/run/yum.pid: another copy is running&quot;`&#xA;   &#xA;   if [ &quot;$islock&quot; != &quot;&quot; ]; then&#xA;     exit 10&#xA;   fi&#xA;   &#xA;   isnotconnected=`echo $result | grep -E &quot;There was an error communicating with RHN&quot;`&#xA;   if [ &quot;$isnotconnected&quot; != &quot;&quot; ]; then&#xA;     exit 9&#xA;   fi&#xA;   &#xA;   isnotconnected=`echo $result | grep -E &quot;This system is not registered with RHN&quot;`&#xA;   if [ &quot;$isnotconnected&quot; != &quot;&quot; ]; then&#xA;     exit 9&#xA;   fi&#xA;   &#xA;    isnotconnected=`echo $result | grep -E &quot;No Repositories Available to Set Up&quot;`&#xA;   if [ &quot;$isnotconnected&quot; != &quot;&quot; ]; then&#xA;     exit 9&#xA;   fi&#xA;    isnotconnected=`echo $result | grep -E &quot;Error Class Code: 9 Error Class Info: Invalid System Credentials&quot;`&#xA;   if [ &quot;$isnotconnected&quot; != &quot;&quot; ]; then&#xA;     exit 9&#xA;   fi&#xA;    isscriptletfailed=`echo $result | grep -E &quot;error:&quot; | grep -E &quot;scriptlet failed, exit status 255&quot;`&#xA;    if [ &quot;$isscriptletfailed&quot; != &quot;&quot; ]; then&#xA;     exit 6&#xA;   fi&#xA;   if [ $status -ne 0 ];then&#xA;     exit 7&#xA;   fi &#xA; fi&#xA;}&#xA;updatepk systemd  &#xA;&#xA;exit 0" />
          </Args>
        </Cmd>
      </Cmds>
    </Patch>
    <Patch UniqueFilename="*systemd-debuginfo-208-11.el7_0.2.i686.rpm" Silent="CRSNo" Reboot="RNo" Download="DManual">
      <Name>systemd-debuginfo-208-11.el7_0.2.i686.rpm</Name>
      <Comments />
      <URL />
      <State>Enabled</State>
      <Files>
        <File>
          <Path>systemd-debuginfo::i686</Path>
          <FileDate>0001-01-01T00:00:00.0000000</FileDate>
          <FileSize>0</FileSize>
          <Checksum>5a892b4acf0f95281ce74051679811292839671353c2d781db07bfeeb146acc2</Checksum>
          <Version>208-11.el7_0.2</Version>
          <CommandID>e</CommandID>
          <Flags>P</Flags>
        </File>
      </Files>
      <Products>
        <ID>55410</ID>
      </Products>
      <Platforms>
        <ID>rhel7_x86_64</ID>
      </Platforms>
      <CustVars />
      <Cmds>
        <Cmd Type="shellscript">
          <Args>
            <Arg N="scriptcode" V="#!/bin/bash&#xA;&#xA;function updatepk()&#xA;{&#xA; if [ ! -z $1 ]; then&#xA;   if [ -e /var/run/yum.pid ];then &#xA;    exit 10  &#xA;   fi&#xA;   result=`yum -y update $1 2&gt;&amp;1` &#xA;   status=$? &#xA;   commandexist=`echo $result | grep -E &quot;yum: command not found&quot;`&#xA;   if [ &quot;$commandexist&quot; != &quot;&quot; ]; then&#xA;     exit 8&#xA;   fi&#xA;   &#xA;    commandexist=`echo $result | grep -E &quot;yum: No such file or directory&quot;`&#xA;   if [ &quot;$commandexist&quot; != &quot;&quot; ]; then&#xA;     exit 8&#xA;   fi&#xA;   &#xA;   islock=`echo $result | grep -E &quot;lock /var/run/yum.pid&quot;`&#xA;   &#xA;   if [ &quot;$islock&quot; != &quot;&quot; ]; then&#xA;     exit 10&#xA;   fi&#xA;   &#xA;   islock=`echo $result | grep -E &quot;/var/run/yum.pid: another copy is running&quot;`&#xA;   &#xA;   if [ &quot;$islock&quot; != &quot;&quot; ]; then&#xA;     exit 10&#xA;   fi&#xA;   &#xA;   isnotconnected=`echo $result | grep -E &quot;There was an error communicating with RHN&quot;`&#xA;   if [ &quot;$isnotconnected&quot; != &quot;&quot; ]; then&#xA;     exit 9&#xA;   fi&#xA;   &#xA;   isnotconnected=`echo $result | grep -E &quot;This system is not registered with RHN&quot;`&#xA;   if [ &quot;$isnotconnected&quot; != &quot;&quot; ]; then&#xA;     exit 9&#xA;   fi&#xA;   &#xA;    isnotconnected=`echo $result | grep -E &quot;No Repositories Available to Set Up&quot;`&#xA;   if [ &quot;$isnotconnected&quot; != &quot;&quot; ]; then&#xA;     exit 9&#xA;   fi&#xA;    isnotconnected=`echo $result | grep -E &quot;Error Class Code: 9 Error Class Info: Invalid System Credentials&quot;`&#xA;   if [ &quot;$isnotconnected&quot; != &quot;&quot; ]; then&#xA;     exit 9&#xA;   fi&#xA;    isscriptletfailed=`echo $result | grep -E &quot;error:&quot; | grep -E &quot;scriptlet failed, exit status 255&quot;`&#xA;    if [ &quot;$isscriptletfailed&quot; != &quot;&quot; ]; then&#xA;     exit 6&#xA;   fi&#xA;   if [ $status -ne 0 ];then&#xA;     exit 7&#xA;   fi &#xA; fi&#xA;}&#xA;updatepk systemd-debuginfo  &#xA;&#xA;exit 0" />
          </Args>
        </Cmd>
      </Cmds>
    </Patch>
    <Patch UniqueFilename="*systemd-debuginfo-208-11.el7_0.2.x86_64.rpm" Silent="CRSNo" Reboot="RNo" Download="DManual">
      <Name>systemd-debuginfo-208-11.el7_0.2.x86_64.rpm</Name>
      <Comments />
      <URL />
      <State>Enabled</State>
      <Files>
        <File>
          <Path>systemd-debuginfo::x86_64</Path>
          <FileDate>0001-01-01T00:00:00.0000000</FileDate>
          <FileSize>0</FileSize>
          <Checksum>7a84b9f2d39380e7dbe3da965e846193f7946dc17533fe7506407cb559cbcbd0</Checksum>
          <Version>208-11.el7_0.2</Version>
          <CommandID>e</CommandID>
          <Flags>P</Flags>
        </File>
      </Files>
      <Products>
        <ID>55411</ID>
      </Products>
      <Platforms>
        <ID>rhel7_x86_64</ID>
      </Platforms>
      <CustVars />
      <Cmds>
        <Cmd Type="shellscript">
          <Args>
            <Arg N="scriptcode" V="#!/bin/bash&#xA;&#xA;function updatepk()&#xA;{&#xA; if [ ! -z $1 ]; then&#xA;   if [ -e /var/run/yum.pid ];then &#xA;    exit 10  &#xA;   fi&#xA;   result=`yum -y update $1 2&gt;&amp;1` &#xA;   status=$? &#xA;   commandexist=`echo $result | grep -E &quot;yum: command not found&quot;`&#xA;   if [ &quot;$commandexist&quot; != &quot;&quot; ]; then&#xA;     exit 8&#xA;   fi&#xA;   &#xA;    commandexist=`echo $result | grep -E &quot;yum: No such file or directory&quot;`&#xA;   if [ &quot;$commandexist&quot; != &quot;&quot; ]; then&#xA;     exit 8&#xA;   fi&#xA;   &#xA;   islock=`echo $result | grep -E &quot;lock /var/run/yum.pid&quot;`&#xA;   &#xA;   if [ &quot;$islock&quot; != &quot;&quot; ]; then&#xA;     exit 10&#xA;   fi&#xA;   &#xA;   islock=`echo $result | grep -E &quot;/var/run/yum.pid: another copy is running&quot;`&#xA;   &#xA;   if [ &quot;$islock&quot; != &quot;&quot; ]; then&#xA;     exit 10&#xA;   fi&#xA;   &#xA;   isnotconnected=`echo $result | grep -E &quot;There was an error communicating with RHN&quot;`&#xA;   if [ &quot;$isnotconnected&quot; != &quot;&quot; ]; then&#xA;     exit 9&#xA;   fi&#xA;   &#xA;   isnotconnected=`echo $result | grep -E &quot;This system is not registered with RHN&quot;`&#xA;   if [ &quot;$isnotconnected&quot; != &quot;&quot; ]; then&#xA;     exit 9&#xA;   fi&#xA;   &#xA;    isnotconnected=`echo $result | grep -E &quot;No Repositories Available to Set Up&quot;`&#xA;   if [ &quot;$isnotconnected&quot; != &quot;&quot; ]; then&#xA;     exit 9&#xA;   fi&#xA;    isnotconnected=`echo $result | grep -E &quot;Error Class Code: 9 Error Class Info: Invalid System Credentials&quot;`&#xA;   if [ &quot;$isnotconnected&quot; != &quot;&quot; ]; then&#xA;     exit 9&#xA;   fi&#xA;    isscriptletfailed=`echo $result | grep -E &quot;error:&quot; | grep -E &quot;scriptlet failed, exit status 255&quot;`&#xA;    if [ &quot;$isscriptletfailed&quot; != &quot;&quot; ]; then&#xA;     exit 6&#xA;   fi&#xA;   if [ $status -ne 0 ];then&#xA;     exit 7&#xA;   fi &#xA; fi&#xA;}&#xA;updatepk systemd-debuginfo  &#xA;&#xA;exit 0" />
          </Args>
        </Cmd>
      </Cmds>
    </Patch>
    <Patch UniqueFilename="*systemd-devel-208-11.el7_0.2.i686.rpm" Silent="CRSNo" Reboot="RNo" Download="DManual">
      <Name>systemd-devel-208-11.el7_0.2.i686.rpm</Name>
      <Comments />
      <URL />
      <State>Enabled</State>
      <Files>
        <File>
          <Path>systemd-devel::i686</Path>
          <FileDate>0001-01-01T00:00:00.0000000</FileDate>
          <FileSize>0</FileSize>
          <Checksum>a6380e0be58e28df94826abddf6adb7bbccbb7381cad6a504877840431a54e5c</Checksum>
          <Version>208-11.el7_0.2</Version>
          <CommandID>e</CommandID>
          <Flags>P</Flags>
        </File>
      </Files>
      <Products>
        <ID>55412</ID>
      </Products>
      <Platforms>
        <ID>rhel7_x86_64</ID>
      </Platforms>
      <CustVars />
      <Cmds>
        <Cmd Type="shellscript">
          <Args>
            <Arg N="scriptcode" V="#!/bin/bash&#xA;&#xA;function updatepk()&#xA;{&#xA; if [ ! -z $1 ]; then&#xA;   if [ -e /var/run/yum.pid ];then &#xA;    exit 10  &#xA;   fi&#xA;   result=`yum -y update $1 2&gt;&amp;1` &#xA;   status=$? &#xA;   commandexist=`echo $result | grep -E &quot;yum: command not found&quot;`&#xA;   if [ &quot;$commandexist&quot; != &quot;&quot; ]; then&#xA;     exit 8&#xA;   fi&#xA;   &#xA;    commandexist=`echo $result | grep -E &quot;yum: No such file or directory&quot;`&#xA;   if [ &quot;$commandexist&quot; != &quot;&quot; ]; then&#xA;     exit 8&#xA;   fi&#xA;   &#xA;   islock=`echo $result | grep -E &quot;lock /var/run/yum.pid&quot;`&#xA;   &#xA;   if [ &quot;$islock&quot; != &quot;&quot; ]; then&#xA;     exit 10&#xA;   fi&#xA;   &#xA;   islock=`echo $result | grep -E &quot;/var/run/yum.pid: another copy is running&quot;`&#xA;   &#xA;   if [ &quot;$islock&quot; != &quot;&quot; ]; then&#xA;     exit 10&#xA;   fi&#xA;   &#xA;   isnotconnected=`echo $result | grep -E &quot;There was an error communicating with RHN&quot;`&#xA;   if [ &quot;$isnotconnected&quot; != &quot;&quot; ]; then&#xA;     exit 9&#xA;   fi&#xA;   &#xA;   isnotconnected=`echo $result | grep -E &quot;This system is not registered with RHN&quot;`&#xA;   if [ &quot;$isnotconnected&quot; != &quot;&quot; ]; then&#xA;     exit 9&#xA;   fi&#xA;   &#xA;    isnotconnected=`echo $result | grep -E &quot;No Repositories Available to Set Up&quot;`&#xA;   if [ &quot;$isnotconnected&quot; != &quot;&quot; ]; then&#xA;     exit 9&#xA;   fi&#xA;    isnotconnected=`echo $result | grep -E &quot;Error Class Code: 9 Error Class Info: Invalid System Credentials&quot;`&#xA;   if [ &quot;$isnotconnected&quot; != &quot;&quot; ]; then&#xA;     exit 9&#xA;   fi&#xA;    isscriptletfailed=`echo $result | grep -E &quot;error:&quot; | grep -E &quot;scriptlet failed, exit status 255&quot;`&#xA;    if [ &quot;$isscriptletfailed&quot; != &quot;&quot; ]; then&#xA;     exit 6&#xA;   fi&#xA;   if [ $status -ne 0 ];then&#xA;     exit 7&#xA;   fi &#xA; fi&#xA;}&#xA;updatepk systemd-devel  &#xA;&#xA;exit 0" />
          </Args>
        </Cmd>
      </Cmds>
    </Patch>
    <Patch UniqueFilename="*systemd-devel-208-11.el7_0.2.x86_64.rpm" Silent="CRSNo" Reboot="RNo" Download="DManual">
      <Name>systemd-devel-208-11.el7_0.2.x86_64.rpm</Name>
      <Comments />
      <URL />
      <State>Enabled</State>
      <Files>
        <File>
          <Path>systemd-devel::x86_64</Path>
          <FileDate>0001-01-01T00:00:00.0000000</FileDate>
          <FileSize>0</FileSize>
          <Checksum>2f47942e41a66ad948bef1271c98bba80349139b5635cd433c1bb605f82c4e19</Checksum>
          <Version>208-11.el7_0.2</Version>
          <CommandID>e</CommandID>
          <Flags>P</Flags>
        </File>
      </Files>
      <Products>
        <ID>55413</ID>
      </Products>
      <Platforms>
        <ID>rhel7_x86_64</ID>
      </Platforms>
      <CustVars />
      <Cmds>
        <Cmd Type="shellscript">
          <Args>
            <Arg N="scriptcode" V="#!/bin/bash&#xA;&#xA;function updatepk()&#xA;{&#xA; if [ ! -z $1 ]; then&#xA;   if [ -e /var/run/yum.pid ];then &#xA;    exit 10  &#xA;   fi&#xA;   result=`yum -y update $1 2&gt;&amp;1` &#xA;   status=$? &#xA;   commandexist=`echo $result | grep -E &quot;yum: command not found&quot;`&#xA;   if [ &quot;$commandexist&quot; != &quot;&quot; ]; then&#xA;     exit 8&#xA;   fi&#xA;   &#xA;    commandexist=`echo $result | grep -E &quot;yum: No such file or directory&quot;`&#xA;   if [ &quot;$commandexist&quot; != &quot;&quot; ]; then&#xA;     exit 8&#xA;   fi&#xA;   &#xA;   islock=`echo $result | grep -E &quot;lock /var/run/yum.pid&quot;`&#xA;   &#xA;   if [ &quot;$islock&quot; != &quot;&quot; ]; then&#xA;     exit 10&#xA;   fi&#xA;   &#xA;   islock=`echo $result | grep -E &quot;/var/run/yum.pid: another copy is running&quot;`&#xA;   &#xA;   if [ &quot;$islock&quot; != &quot;&quot; ]; then&#xA;     exit 10&#xA;   fi&#xA;   &#xA;   isnotconnected=`echo $result | grep -E &quot;There was an error communicating with RHN&quot;`&#xA;   if [ &quot;$isnotconnected&quot; != &quot;&quot; ]; then&#xA;     exit 9&#xA;   fi&#xA;   &#xA;   isnotconnected=`echo $result | grep -E &quot;This system is not registered with RHN&quot;`&#xA;   if [ &quot;$isnotconnected&quot; != &quot;&quot; ]; then&#xA;     exit 9&#xA;   fi&#xA;   &#xA;    isnotconnected=`echo $result | grep -E &quot;No Repositories Available to Set Up&quot;`&#xA;   if [ &quot;$isnotconnected&quot; != &quot;&quot; ]; then&#xA;     exit 9&#xA;   fi&#xA;    isnotconnected=`echo $result | grep -E &quot;Error Class Code: 9 Error Class Info: Invalid System Credentials&quot;`&#xA;   if [ &quot;$isnotconnected&quot; != &quot;&quot; ]; then&#xA;     exit 9&#xA;   fi&#xA;    isscriptletfailed=`echo $result | grep -E &quot;error:&quot; | grep -E &quot;scriptlet failed, exit status 255&quot;`&#xA;    if [ &quot;$isscriptletfailed&quot; != &quot;&quot; ]; then&#xA;     exit 6&#xA;   fi&#xA;   if [ $status -ne 0 ];then&#xA;     exit 7&#xA;   fi &#xA; fi&#xA;}&#xA;updatepk systemd-devel  &#xA;&#xA;exit 0" />
          </Args>
        </Cmd>
      </Cmds>
    </Patch>
    <Patch UniqueFilename="*systemd-journal-gateway-208-11.el7_0.2.x86_64.rpm" Silent="CRSNo" Reboot="RNo" Download="DManual">
      <Name>systemd-journal-gateway-208-11.el7_0.2.x86_64.rpm</Name>
      <Comments />
      <URL />
      <State>Enabled</State>
      <Files>
        <File>
          <Path>systemd-journal-gateway::x86_64</Path>
          <FileDate>0001-01-01T00:00:00.0000000</FileDate>
          <FileSize>0</FileSize>
          <Checksum>4b2360b4d955848899643551b1c7e9dd015576403efc16b46166ecf837f84ff2</Checksum>
          <Version>208-11.el7_0.2</Version>
          <CommandID>e</CommandID>
          <Flags>P</Flags>
        </File>
      </Files>
      <Products>
        <ID>55414</ID>
      </Products>
      <Platforms>
        <ID>rhel7_x86_64</ID>
      </Platforms>
      <CustVars />
      <Cmds>
        <Cmd Type="shellscript">
          <Args>
            <Arg N="scriptcode" V="#!/bin/bash&#xA;&#xA;function updatepk()&#xA;{&#xA; if [ ! -z $1 ]; then&#xA;   if [ -e /var/run/yum.pid ];then &#xA;    exit 10  &#xA;   fi&#xA;   result=`yum -y update $1 2&gt;&amp;1` &#xA;   status=$? &#xA;   commandexist=`echo $result | grep -E &quot;yum: command not found&quot;`&#xA;   if [ &quot;$commandexist&quot; != &quot;&quot; ]; then&#xA;     exit 8&#xA;   fi&#xA;   &#xA;    commandexist=`echo $result | grep -E &quot;yum: No such file or directory&quot;`&#xA;   if [ &quot;$commandexist&quot; != &quot;&quot; ]; then&#xA;     exit 8&#xA;   fi&#xA;   &#xA;   islock=`echo $result | grep -E &quot;lock /var/run/yum.pid&quot;`&#xA;   &#xA;   if [ &quot;$islock&quot; != &quot;&quot; ]; then&#xA;     exit 10&#xA;   fi&#xA;   &#xA;   islock=`echo $result | grep -E &quot;/var/run/yum.pid: another copy is running&quot;`&#xA;   &#xA;   if [ &quot;$islock&quot; != &quot;&quot; ]; then&#xA;     exit 10&#xA;   fi&#xA;   &#xA;   isnotconnected=`echo $result | grep -E &quot;There was an error communicating with RHN&quot;`&#xA;   if [ &quot;$isnotconnected&quot; != &quot;&quot; ]; then&#xA;     exit 9&#xA;   fi&#xA;   &#xA;   isnotconnected=`echo $result | grep -E &quot;This system is not registered with RHN&quot;`&#xA;   if [ &quot;$isnotconnected&quot; != &quot;&quot; ]; then&#xA;     exit 9&#xA;   fi&#xA;   &#xA;    isnotconnected=`echo $result | grep -E &quot;No Repositories Available to Set Up&quot;`&#xA;   if [ &quot;$isnotconnected&quot; != &quot;&quot; ]; then&#xA;     exit 9&#xA;   fi&#xA;    isnotconnected=`echo $result | grep -E &quot;Error Class Code: 9 Error Class Info: Invalid System Credentials&quot;`&#xA;   if [ &quot;$isnotconnected&quot; != &quot;&quot; ]; then&#xA;     exit 9&#xA;   fi&#xA;    isscriptletfailed=`echo $result | grep -E &quot;error:&quot; | grep -E &quot;scriptlet failed, exit status 255&quot;`&#xA;    if [ &quot;$isscriptletfailed&quot; != &quot;&quot; ]; then&#xA;     exit 6&#xA;   fi&#xA;   if [ $status -ne 0 ];then&#xA;     exit 7&#xA;   fi &#xA; fi&#xA;}&#xA;updatepk systemd-journal-gateway  &#xA;&#xA;exit 0" />
          </Args>
        </Cmd>
      </Cmds>
    </Patch>
    <Patch UniqueFilename="*systemd-libs-208-11.el7_0.2.i686.rpm" Silent="CRSNo" Reboot="RNo" Download="DManual">
      <Name>systemd-libs-208-11.el7_0.2.i686.rpm</Name>
      <Comments />
      <URL />
      <State>Enabled</State>
      <Files>
        <File>
          <Path>systemd-libs::i686</Path>
          <FileDate>0001-01-01T00:00:00.0000000</FileDate>
          <FileSize>0</FileSize>
          <Checksum>9a0319feb6dfd4acc12e1b5a2a0a67f045c7bda14e836fad844235fdb8babc16</Checksum>
          <Version>208-11.el7_0.2</Version>
          <CommandID>e</CommandID>
          <Flags>P</Flags>
        </File>
      </Files>
      <Products>
        <ID>55415</ID>
      </Products>
      <Platforms>
        <ID>rhel7_x86_64</ID>
      </Platforms>
      <CustVars />
      <Cmds>
        <Cmd Type="shellscript">
          <Args>
            <Arg N="scriptcode" V="#!/bin/bash&#xA;&#xA;function updatepk()&#xA;{&#xA; if [ ! -z $1 ]; then&#xA;   if [ -e /var/run/yum.pid ];then &#xA;    exit 10  &#xA;   fi&#xA;   result=`yum -y update $1 2&gt;&amp;1` &#xA;   status=$? &#xA;   commandexist=`echo $result | grep -E &quot;yum: command not found&quot;`&#xA;   if [ &quot;$commandexist&quot; != &quot;&quot; ]; then&#xA;     exit 8&#xA;   fi&#xA;   &#xA;    commandexist=`echo $result | grep -E &quot;yum: No such file or directory&quot;`&#xA;   if [ &quot;$commandexist&quot; != &quot;&quot; ]; then&#xA;     exit 8&#xA;   fi&#xA;   &#xA;   islock=`echo $result | grep -E &quot;lock /var/run/yum.pid&quot;`&#xA;   &#xA;   if [ &quot;$islock&quot; != &quot;&quot; ]; then&#xA;     exit 10&#xA;   fi&#xA;   &#xA;   islock=`echo $result | grep -E &quot;/var/run/yum.pid: another copy is running&quot;`&#xA;   &#xA;   if [ &quot;$islock&quot; != &quot;&quot; ]; then&#xA;     exit 10&#xA;   fi&#xA;   &#xA;   isnotconnected=`echo $result | grep -E &quot;There was an error communicating with RHN&quot;`&#xA;   if [ &quot;$isnotconnected&quot; != &quot;&quot; ]; then&#xA;     exit 9&#xA;   fi&#xA;   &#xA;   isnotconnected=`echo $result | grep -E &quot;This system is not registered with RHN&quot;`&#xA;   if [ &quot;$isnotconnected&quot; != &quot;&quot; ]; then&#xA;     exit 9&#xA;   fi&#xA;   &#xA;    isnotconnected=`echo $result | grep -E &quot;No Repositories Available to Set Up&quot;`&#xA;   if [ &quot;$isnotconnected&quot; != &quot;&quot; ]; then&#xA;     exit 9&#xA;   fi&#xA;    isnotconnected=`echo $result | grep -E &quot;Error Class Code: 9 Error Class Info: Invalid System Credentials&quot;`&#xA;   if [ &quot;$isnotconnected&quot; != &quot;&quot; ]; then&#xA;     exit 9&#xA;   fi&#xA;    isscriptletfailed=`echo $result | grep -E &quot;error:&quot; | grep -E &quot;scriptlet failed, exit status 255&quot;`&#xA;    if [ &quot;$isscriptletfailed&quot; != &quot;&quot; ]; then&#xA;     exit 6&#xA;   fi&#xA;   if [ $status -ne 0 ];then&#xA;     exit 7&#xA;   fi &#xA; fi&#xA;}&#xA;updatepk systemd-libs  &#xA;&#xA;exit 0" />
          </Args>
        </Cmd>
      </Cmds>
    </Patch>
    <Patch UniqueFilename="*systemd-libs-208-11.el7_0.2.x86_64.rpm" Silent="CRSNo" Reboot="RNo" Download="DManual">
      <Name>systemd-libs-208-11.el7_0.2.x86_64.rpm</Name>
      <Comments />
      <URL />
      <State>Enabled</State>
      <Files>
        <File>
          <Path>systemd-libs::x86_64</Path>
          <FileDate>0001-01-01T00:00:00.0000000</FileDate>
          <FileSize>0</FileSize>
          <Checksum>828ba3f02f7e96ee45d49c5f239d2a641fc5965c615b53062dc19eea3a954f82</Checksum>
          <Version>208-11.el7_0.2</Version>
          <CommandID>e</CommandID>
          <Flags>P</Flags>
        </File>
      </Files>
      <Products>
        <ID>55416</ID>
      </Products>
      <Platforms>
        <ID>rhel7_x86_64</ID>
      </Platforms>
      <CustVars />
      <Cmds>
        <Cmd Type="shellscript">
          <Args>
            <Arg N="scriptcode" V="#!/bin/bash&#xA;&#xA;function updatepk()&#xA;{&#xA; if [ ! -z $1 ]; then&#xA;   if [ -e /var/run/yum.pid ];then &#xA;    exit 10  &#xA;   fi&#xA;   result=`yum -y update $1 2&gt;&amp;1` &#xA;   status=$? &#xA;   commandexist=`echo $result | grep -E &quot;yum: command not found&quot;`&#xA;   if [ &quot;$commandexist&quot; != &quot;&quot; ]; then&#xA;     exit 8&#xA;   fi&#xA;   &#xA;    commandexist=`echo $result | grep -E &quot;yum: No such file or directory&quot;`&#xA;   if [ &quot;$commandexist&quot; != &quot;&quot; ]; then&#xA;     exit 8&#xA;   fi&#xA;   &#xA;   islock=`echo $result | grep -E &quot;lock /var/run/yum.pid&quot;`&#xA;   &#xA;   if [ &quot;$islock&quot; != &quot;&quot; ]; then&#xA;     exit 10&#xA;   fi&#xA;   &#xA;   islock=`echo $result | grep -E &quot;/var/run/yum.pid: another copy is running&quot;`&#xA;   &#xA;   if [ &quot;$islock&quot; != &quot;&quot; ]; then&#xA;     exit 10&#xA;   fi&#xA;   &#xA;   isnotconnected=`echo $result | grep -E &quot;There was an error communicating with RHN&quot;`&#xA;   if [ &quot;$isnotconnected&quot; != &quot;&quot; ]; then&#xA;     exit 9&#xA;   fi&#xA;   &#xA;   isnotconnected=`echo $result | grep -E &quot;This system is not registered with RHN&quot;`&#xA;   if [ &quot;$isnotconnected&quot; != &quot;&quot; ]; then&#xA;     exit 9&#xA;   fi&#xA;   &#xA;    isnotconnected=`echo $result | grep -E &quot;No Repositories Available to Set Up&quot;`&#xA;   if [ &quot;$isnotconnected&quot; != &quot;&quot; ]; then&#xA;     exit 9&#xA;   fi&#xA;    isnotconnected=`echo $result | grep -E &quot;Error Class Code: 9 Error Class Info: Invalid System Credentials&quot;`&#xA;   if [ &quot;$isnotconnected&quot; != &quot;&quot; ]; then&#xA;     exit 9&#xA;   fi&#xA;    isscriptletfailed=`echo $result | grep -E &quot;error:&quot; | grep -E &quot;scriptlet failed, exit status 255&quot;`&#xA;    if [ &quot;$isscriptletfailed&quot; != &quot;&quot; ]; then&#xA;     exit 6&#xA;   fi&#xA;   if [ $status -ne 0 ];then&#xA;     exit 7&#xA;   fi &#xA; fi&#xA;}&#xA;updatepk systemd-libs  &#xA;&#xA;exit 0" />
          </Args>
        </Cmd>
      </Cmds>
    </Patch>
    <Patch UniqueFilename="*systemd-python-208-11.el7_0.2.x86_64.rpm" Silent="CRSNo" Reboot="RNo" Download="DManual">
      <Name>systemd-python-208-11.el7_0.2.x86_64.rpm</Name>
      <Comments />
      <URL />
      <State>Enabled</State>
      <Files>
        <File>
          <Path>systemd-python::x86_64</Path>
          <FileDate>0001-01-01T00:00:00.0000000</FileDate>
          <FileSize>0</FileSize>
          <Checksum>e1dec9a49242522fd80d58fc5976a7cf1bda7ed206611ec32acb199e3c14eba4</Checksum>
          <Version>208-11.el7_0.2</Version>
          <CommandID>e</CommandID>
          <Flags>P</Flags>
        </File>
      </Files>
      <Products>
        <ID>55417</ID>
      </Products>
      <Platforms>
        <ID>rhel7_x86_64</ID>
      </Platforms>
      <CustVars />
      <Cmds>
        <Cmd Type="shellscript">
          <Args>
            <Arg N="scriptcode" V="#!/bin/bash&#xA;&#xA;function updatepk()&#xA;{&#xA; if [ ! -z $1 ]; then&#xA;   if [ -e /var/run/yum.pid ];then &#xA;    exit 10  &#xA;   fi&#xA;   result=`yum -y update $1 2&gt;&amp;1` &#xA;   status=$? &#xA;   commandexist=`echo $result | grep -E &quot;yum: command not found&quot;`&#xA;   if [ &quot;$commandexist&quot; != &quot;&quot; ]; then&#xA;     exit 8&#xA;   fi&#xA;   &#xA;    commandexist=`echo $result | grep -E &quot;yum: No such file or directory&quot;`&#xA;   if [ &quot;$commandexist&quot; != &quot;&quot; ]; then&#xA;     exit 8&#xA;   fi&#xA;   &#xA;   islock=`echo $result | grep -E &quot;lock /var/run/yum.pid&quot;`&#xA;   &#xA;   if [ &quot;$islock&quot; != &quot;&quot; ]; then&#xA;     exit 10&#xA;   fi&#xA;   &#xA;   islock=`echo $result | grep -E &quot;/var/run/yum.pid: another copy is running&quot;`&#xA;   &#xA;   if [ &quot;$islock&quot; != &quot;&quot; ]; then&#xA;     exit 10&#xA;   fi&#xA;   &#xA;   isnotconnected=`echo $result | grep -E &quot;There was an error communicating with RHN&quot;`&#xA;   if [ &quot;$isnotconnected&quot; != &quot;&quot; ]; then&#xA;     exit 9&#xA;   fi&#xA;   &#xA;   isnotconnected=`echo $result | grep -E &quot;This system is not registered with RHN&quot;`&#xA;   if [ &quot;$isnotconnected&quot; != &quot;&quot; ]; then&#xA;     exit 9&#xA;   fi&#xA;   &#xA;    isnotconnected=`echo $result | grep -E &quot;No Repositories Available to Set Up&quot;`&#xA;   if [ &quot;$isnotconnected&quot; != &quot;&quot; ]; then&#xA;     exit 9&#xA;   fi&#xA;    isnotconnected=`echo $result | grep -E &quot;Error Class Code: 9 Error Class Info: Invalid System Credentials&quot;`&#xA;   if [ &quot;$isnotconnected&quot; != &quot;&quot; ]; then&#xA;     exit 9&#xA;   fi&#xA;    isscriptletfailed=`echo $result | grep -E &quot;error:&quot; | grep -E &quot;scriptlet failed, exit status 255&quot;`&#xA;    if [ &quot;$isscriptletfailed&quot; != &quot;&quot; ]; then&#xA;     exit 6&#xA;   fi&#xA;   if [ $status -ne 0 ];then&#xA;     exit 7&#xA;   fi &#xA; fi&#xA;}&#xA;updatepk systemd-python  &#xA;&#xA;exit 0" />
          </Args>
        </Cmd>
      </Cmds>
    </Patch>
    <Patch UniqueFilename="*systemd-sysv-208-11.el7_0.2.x86_64.rpm" Silent="CRSNo" Reboot="RNo" Download="DManual">
      <Name>systemd-sysv-208-11.el7_0.2.x86_64.rpm</Name>
      <Comments />
      <URL />
      <State>Enabled</State>
      <Files>
        <File>
          <Path>systemd-sysv::x86_64</Path>
          <FileDate>0001-01-01T00:00:00.0000000</FileDate>
          <FileSize>0</FileSize>
          <Checksum>54464efa9f301e09644c60d08fef522d82aafeef7f2e29796310ac1b617a6fa1</Checksum>
          <Version>208-11.el7_0.2</Version>
          <CommandID>e</CommandID>
          <Flags>P</Flags>
        </File>
      </Files>
      <Products>
        <ID>55418</ID>
      </Products>
      <Platforms>
        <ID>rhel7_x86_64</ID>
      </Platforms>
      <CustVars />
      <Cmds>
        <Cmd Type="shellscript">
          <Args>
            <Arg N="scriptcode" V="#!/bin/bash&#xA;&#xA;function updatepk()&#xA;{&#xA; if [ ! -z $1 ]; then&#xA;   if [ -e /var/run/yum.pid ];then &#xA;    exit 10  &#xA;   fi&#xA;   result=`yum -y update $1 2&gt;&amp;1` &#xA;   status=$? &#xA;   commandexist=`echo $result | grep -E &quot;yum: command not found&quot;`&#xA;   if [ &quot;$commandexist&quot; != &quot;&quot; ]; then&#xA;     exit 8&#xA;   fi&#xA;   &#xA;    commandexist=`echo $result | grep -E &quot;yum: No such file or directory&quot;`&#xA;   if [ &quot;$commandexist&quot; != &quot;&quot; ]; then&#xA;     exit 8&#xA;   fi&#xA;   &#xA;   islock=`echo $result | grep -E &quot;lock /var/run/yum.pid&quot;`&#xA;   &#xA;   if [ &quot;$islock&quot; != &quot;&quot; ]; then&#xA;     exit 10&#xA;   fi&#xA;   &#xA;   islock=`echo $result | grep -E &quot;/var/run/yum.pid: another copy is running&quot;`&#xA;   &#xA;   if [ &quot;$islock&quot; != &quot;&quot; ]; then&#xA;     exit 10&#xA;   fi&#xA;   &#xA;   isnotconnected=`echo $result | grep -E &quot;There was an error communicating with RHN&quot;`&#xA;   if [ &quot;$isnotconnected&quot; != &quot;&quot; ]; then&#xA;     exit 9&#xA;   fi&#xA;   &#xA;   isnotconnected=`echo $result | grep -E &quot;This system is not registered with RHN&quot;`&#xA;   if [ &quot;$isnotconnected&quot; != &quot;&quot; ]; then&#xA;     exit 9&#xA;   fi&#xA;   &#xA;    isnotconnected=`echo $result | grep -E &quot;No Repositories Available to Set Up&quot;`&#xA;   if [ &quot;$isnotconnected&quot; != &quot;&quot; ]; then&#xA;     exit 9&#xA;   fi&#xA;    isnotconnected=`echo $result | grep -E &quot;Error Class Code: 9 Error Class Info: Invalid System Credentials&quot;`&#xA;   if [ &quot;$isnotconnected&quot; != &quot;&quot; ]; then&#xA;     exit 9&#xA;   fi&#xA;    isscriptletfailed=`echo $result | grep -E &quot;error:&quot; | grep -E &quot;scriptlet failed, exit status 255&quot;`&#xA;    if [ &quot;$isscriptletfailed&quot; != &quot;&quot; ]; then&#xA;     exit 6&#xA;   fi&#xA;   if [ $status -ne 0 ];then&#xA;     exit 7&#xA;   fi &#xA; fi&#xA;}&#xA;updatepk systemd-sysv  &#xA;&#xA;exit 0" />
          </Args>
        </Cmd>
      </Cmds>
    </Patch>
  </Patches>
  <PublishDate>2014-07-29T00:00:00.0000000</PublishDate>
  <Title>systemd bug fix update</Title>
  <Description>
        
systemd is a system and service manager for Linux, compatible with the SysV and
LSB init scripts. It provides aggressive parallelization capabilities, uses
socket and D-Bus activation for starting services, offers on-demand starting of
daemons, and keeps track of processes using Linux cgroups. In addition, it
supports snapshotting and restoring of the system state, maintains mount and
automount points, and implements an elaborate transactional dependency-based
service control logic. It can also work as a drop-in replacement for sysvinit.
This update fixes the following bugs:
 Prior to this update, the serial-getty@.service unit file did not contain the
Install section. As a consequence, using the "systemctl enable" command to
enable user logins on additional terminals using the getty utility failed. This
update adds the Install section to the serial-getty@.service unit file and user
logins can now be created through getty by "systemctl enable" as expected.
(BZ#1083936)
 Previously, the network.service and network-online.target systemd units did
not have any configuration to determine the order in which they execute.
Consequently, services that were set up with the "After=network-online.target"
parameter were not properly executed after network.service. As a consequence,
services that require network to be online upon their startup (such as the
Corosync Cluster Engine) failed to start. To fix this issue,
network-online.target has been modified to always run after network.target, and
the described problems no longer occur. (BZ#1121650)
Users of systemd are advised to upgrade to these updated packages, which fix
these bugs.
        Note for remediation: Please disable the SELinux for RHEL 4/5 when repairing, or some rpm packages will fail to install.</Description>
  <Severity>5</Severity>
  <Vendor>Redhat</Vendor>
  <MoreInfoURL>https://access.redhat.com/errata/RHBA-2014:0989</MoreInfoURL>
  <FAQURL />
</Vulnerability>